{"cameraMode":{"drawMode":0,"name":"Shaded","section":"Shading Mode"},"sceneLighting":false,"audioPlay":false,"sceneViewState":{"m_AlwaysRefresh":false,"showFog":true,"showSkybox":false,"showFlares":true,"showImageEffects":true,"showParticleSystems":true,"showVisualEffectGraphs":true,"m_FxEnabled":true},"in2DMode":false,"pivot":{"x":6.500003814697266,"y":0.34200000762939455,"z":25.750001907348634},"rotation":{"x":-0.23945946991443635,"y":-0.0037898733280599119,"z":0.0009354586945846677,"w":-0.9709052443504334},"size":7.002720832824707,"orthographic":false}